Secweb/__init__.py
Secweb/index.py
Secweb/CacheControl/CacheControlMiddleware.py
Secweb/CacheControl/__init__.py
Secweb/ClearSiteData/ClearSiteDataMiddleware.py
Secweb/ClearSiteData/__init__.py
Secweb/ContentSecurityPolicy/ContentSecurityPolicyMiddleware.py
Secweb/ContentSecurityPolicy/__init__.py
Secweb/CrossOriginEmbedderPolicy/CrossOriginEmbedderPolicyMiddleware.py
Secweb/CrossOriginEmbedderPolicy/__init__.py
Secweb/CrossOriginOpenerPolicy/CrossOriginOpenerPolicyMiddleware.py
Secweb/CrossOriginOpenerPolicy/__init__.py
Secweb/CrossOriginResourcePolicy/CrossOriginResourcePolicyMiddleware.py
Secweb/CrossOriginResourcePolicy/__init__.py
Secweb/OriginAgentCluster/OriginAgentClusterMiddleware.py
Secweb/OriginAgentCluster/__init__.py
Secweb/ReferrerPolicy/ReferrerPolicyMiddleware.py
Secweb/ReferrerPolicy/__init__.py
Secweb/StrictTransportSecurity/StrictTransportSecurityMiddleware.py
Secweb/StrictTransportSecurity/__init__.py
Secweb/WsStrictTransportSecurity/WsStrictTransportSecurityMiddleware.py
Secweb/WsStrictTransportSecurity/__init__.py
Secweb/XContentTypeOptions/XContentTypeOptionsMiddleware.py
Secweb/XContentTypeOptions/__init__.py
Secweb/XDNSPrefetchControl/XDNSPrefetchControlMiddleware.py
Secweb/XDNSPrefetchControl/__init__.py
Secweb/XDownloadOptions/XDownloadOptionsMiddleware.py
Secweb/XDownloadOptions/__init__.py
Secweb/XFrameOptions/XFrameOptionsMiddleware.py
Secweb/XFrameOptions/__init__.py
Secweb/XPermittedCrossDomainPolicies/XPermittedCrossDomainPoliciesMiddleware.py
Secweb/XPermittedCrossDomainPolicies/__init__.py
Secweb/xXSSProtection/__init__.py
Secweb/xXSSProtection/xXSSProtectionMiddleware.py
secweb-1.25.2.dist-info/licenses/LICENSE
secweb-1.25.2.dist-info/METADATA
secweb-1.25.2.dist-info/WHEEL
secweb-1.25.2.dist-info/top_level.txt
secweb-1.25.2.dist-info/RECORD
