Metadata-Version: 2.4
Name: Secweb
Version: 1.25.2
Summary: Secweb is a pack of security middlewares for fastApi and starlette servers it includes CSP, HSTS, and many more
Author-email: Motagamwala Taha Arif Ali <tahaar5321@gmail.com>
License-Expression: MPL-2.0
Project-URL: Homepage, https://github.com/tmotagam/Secweb
Project-URL: Documentation, https://github.com/tmotagam/Secweb#readme
Project-URL: Repository, https://github.com/tmotagam/Secweb.git
Project-URL: Issues, https://github.com/tmotagam/Secweb/issues
Keywords: fastapi security header,security header,starlette security header,secweb,fastapi csp,starlette csp,csp
Classifier: Programming Language :: Python :: 3
Classifier: Operating System :: OS Independent
Classifier: Development Status :: 5 - Production/Stable
Classifier: Intended Audience :: Developers
Requires-Python: >=3.8
License-File: LICENSE
Dynamic: license-file
